{
  "season": 2026,
  "round": 9,
  "circuitId": "silverstone",
  "winners": [
    {
      "year": 2025,
      "code": "NOR",
      "name": "Lando Norris",
      "constructor": "McLaren",
      "winsHere": 1
    },
    {
      "year": 2024,
      "code": "HAM",
      "name": "Lewis Hamilton",
      "constructor": "Mercedes",
      "winsHere": 9
    },
    {
      "year": 2023,
      "code": "VER",
      "name": "Max Verstappen",
      "constructor": "Red Bull",
      "winsHere": 2
    },
    {
      "year": 2022,
      "code": "SAI",
      "name": "Carlos Sainz",
      "constructor": "Ferrari",
      "winsHere": 1
    },
    {
      "year": 2021,
      "code": "HAM",
      "name": "Lewis Hamilton",
      "constructor": "Mercedes",
      "winsHere": 8
    }
  ]
}
